beetsplug/__init__.py
beetsplug/webrouter/__init__.py
beetsplug/webrouter/config_default.yaml
beetsplug/webrouter/favicon.py
beetsplug/webrouter/static/favicon.ico
beets_webrouter-0.5.0.dist-info/LICENSE
beets_webrouter-0.5.0.dist-info/METADATA
beets_webrouter-0.5.0.dist-info/WHEEL
beets_webrouter-0.5.0.dist-info/top_level.txt
beets_webrouter-0.5.0.dist-info/RECORD
