Metadata-Version: 2.1
Name: beets-webrouter
Version: 0.5.0
Summary: Serve multiple beets APIs on the same IP/port using a single command
Home-page: https://github.com/mgoltzsche/beets-webrouter
Author: Max Goltzsche
License: UNKNOWN
Platform: UNKNOWN
Classifier: Programming Language :: Python :: 3.6
Classifier: License :: OSI Approved :: MIT License
Classifier: Operating System :: OS Independent
License-File: LICENSE
Requires-Dist: beets
Requires-Dist: fastapi
Requires-Dist: flask
Requires-Dist: uvicorn
